HoloRelay/HoloRelay.py
HoloRelay/__init__.py
holorelay-0.1.0.dist-info/licenses/LICENSE
holorelay-0.1.0.dist-info/METADATA
holorelay-0.1.0.dist-info/WHEEL
holorelay-0.1.0.dist-info/top_level.txt
holorelay-0.1.0.dist-info/RECORD
