Metadata-Version: 2.4
Name: HoloRelay
Version: 0.1.0
Summary: A modern way to let AI-agents Communicate
Author: Tristan McBride Sr.
Author-email: "Tristan McBride Sr." <142635792+TristanMcBrideSr@users.noreply.github.com>
Project-URL: Homepage, https://github.com/TristanMcBrideSr
Requires-Python: >=3.10
License-File: LICENSE
Requires-Dist: AgentToAgent
Dynamic: author
Dynamic: license-file
